{"date":"2024-05-21T06:25:08.631Z","courseId":"17","assignment":"AP-Spring03-CA6","trace":{"content":"#ifndef LOGIN_INCLUDE\n#define LOGIN_INCLUDE\n\nclass Login {\npublic:\n    Login(vector<string> input_line);\n    ~Login() {};\nprotected:\nprivate:\n    void checkInputSizeLogin();\n    void checkQuestionMarkLogin();\n    vector<string> input_line;\n\n};\n\n#endif","filename":"/Users/mahdis/Desktop/AP/AP6/include/Login.hpp","identifier":"Save Document","languageId":"cpp","version":157,"lineCount":16},"failed":false}